heybooster/__init__.py
heybooster/exception/__init__.py
heybooster/exception/exception_catcher.py
heybooster/helpers/__init__.py
heybooster/helpers/database/__init__.py
heybooster/helpers/database/mongodb.py
heybooster/helpers/database/opensearch.py
heybooster/helpers/database/postgre.py
heybooster/helpers/email/__init__.py
heybooster/helpers/email/sendpulse.py
heybooster/helpers/email/statics/__init__.py
heybooster/helpers/email/utils/__init__.py
heybooster/helpers/hubspot/__init__.py
heybooster/helpers/hubspot/contacts.py
heybooster/logger/__init__.py
heybooster/logger/cloudwatch/__init__.py
heybooster/logger/cloudwatch/cloudwatch_logger.py
heybooster_toolkit-0.0.40.dist-info/LICENSE
heybooster_toolkit-0.0.40.dist-info/METADATA
heybooster_toolkit-0.0.40.dist-info/WHEEL
heybooster_toolkit-0.0.40.dist-info/top_level.txt
heybooster_toolkit-0.0.40.dist-info/RECORD
