Metadata-Version: 2.1
Name: heybooster-toolkit
Version: 0.0.40
Summary: Heybooster Toolkit
Home-page: https://github.com/hey-booster/heybooster-toolkit
Author: Heybooster
Author-email: hey@heybooster.ai
Project-URL: Bug Tracker, https://github.com/hey-booster/heybooster-toolkit/issues
Classifier: Programming Language :: Python :: 3
Classifier: License :: OSI Approved :: MIT License
Classifier: Operating System :: OS Independent
Requires-Python: >=3.6
License-File: LICENSE
Requires-Dist: pymongo (==3.10.1)
Requires-Dist: requests
Requires-Dist: raven (==6.10.0)
Requires-Dist: boto3 (==1.28.15)
